{
    "percentiles": {
        "5th": -11.708718478761863,
        "25th": -2.4045064619259344,
        "50th": 11.323934455537966,
        "75th": 20.60869262229619,
        "95th": 35.63274920481199
    },
    "median": 11.323934455537966,
    "mean": 10.541325032866062,
    "kde_points": [
        {
            "x": -23.47762691390859,
            "density": 0.0002037411466390582
        },
        {
            "x": -23.12794379215541,
            "density": 0.00026484359210110926
        },
        {
            "x": -22.778260670402233,
            "density": 0.0003394749469318134
        },
        {
            "x": -22.428577548649052,
            "density": 0.00042902220636746585
        },
        {
            "x": -22.07889442689587,
            "density": 0.0005344851440944289
        },
        {
            "x": -21.729211305142694,
            "density": 0.0006563318038925489
        },
        {
            "x": -21.379528183389514,
            "density": 0.000794402699915321
        },
        {
            "x": -21.029845061636333,
            "density": 0.0009478966406027661
        },
        {
            "x": -20.680161939883156,
            "density": 0.00111546307071905
        },
        {
            "x": -20.330478818129976,
            "density": 0.0012954101811327578
        },
        {
            "x": -19.980795696376795,
            "density": 0.0014860170120586432
        },
        {
            "x": -19.631112574623618,
            "density": 0.0016859155066872747
        },
        {
            "x": -19.281429452870437,
            "density": 0.0018944902018217934
        },
        {
            "x": -18.93174633111726,
            "density": 0.0021122340384318638
        },
        {
            "x": -18.58206320936408,
            "density": 0.0023410020038197566
        },
        {
            "x": -18.2323800876109,
            "density": 0.002584120305133733
        },
        {
            "x": -17.88269696585772,
            "density": 0.0028463341710008184
        },
        {
            "x": -17.53301384410454,
            "density": 0.00313360562723631
        },
        {
            "x": -17.18333072235136,
            "density": 0.003452795614558262
        },
        {
            "x": -16.833647600598184,
            "density": 0.0038112755705684994
        },
        {
            "x": -16.483964478845003,
            "density": 0.0042165087592130135
        },
        {
            "x": -16.134281357091822,
            "density": 0.004675623386867377
        },
        {
            "x": -15.784598235338644,
            "density": 0.005194975642820516
        },
        {
            "x": -15.434915113585465,
            "density": 0.005779682452066654
        },
        {
            "x": -15.085231991832284,
            "density": 0.006433101729892036
        },
        {
            "x": -14.735548870079105,
            "density": 0.007156258198730722
        },
        {
            "x": -14.385865748325926,
            "density": 0.007947253007146276
        },
        {
            "x": -14.036182626572748,
            "density": 0.008800744119781377
        },
        {
            "x": -13.686499504819567,
            "density": 0.009707624135505985
        },
        {
            "x": -13.336816383066388,
            "density": 0.010655034737296547
        },
        {
            "x": -12.98713326131321,
            "density": 0.011626830533324722
        },
        {
            "x": -12.637450139560029,
            "density": 0.012604539168007235
        },
        {
            "x": -12.28776701780685,
            "density": 0.013568771471768862
        },
        {
            "x": -11.938083896053671,
            "density": 0.01450093653174368
        },
        {
            "x": -11.58840077430049,
            "density": 0.015385035814421402
        },
        {
            "x": -11.238717652547312,
            "density": 0.016209266913749448
        },
        {
            "x": -10.889034530794133,
            "density": 0.01696717055924586
        },
        {
            "x": -10.539351409040952,
            "density": 0.01765810341976464
        },
        {
            "x": -10.189668287287773,
            "density": 0.01828690602009814
        },
        {
            "x": -9.839985165534594,
            "density": 0.018862748676939857
        },
        {
            "x": -9.490302043781416,
            "density": 0.019397266782109752
        },
        {
            "x": -9.140618922028235,
            "density": 0.019902226148879862
        },
        {
            "x": -8.790935800275056,
            "density": 0.02038707087068494
        },
        {
            "x": -8.441252678521877,
            "density": 0.020856775509302653
        },
        {
            "x": -8.091569556768697,
            "density": 0.021310423226359662
        },
        {
            "x": -7.741886435015518,
            "density": 0.021740841397193112
        },
        {
            "x": -7.392203313262339,
            "density": 0.022135445088171692
        },
        {
            "x": -7.042520191509158,
            "density": 0.022478193337094225
        },
        {
            "x": -6.692837069755978,
            "density": 0.02275230777532306
        },
        {
            "x": -6.343153948002801,
            "density": 0.02294320702232603
        },
        {
            "x": -5.99347082624962,
            "density": 0.02304103585596904
        },
        {
            "x": -5.643787704496443,
            "density": 0.023042247863347708
        },
        {
            "x": -5.2941045827432625,
            "density": 0.02294992187006973
        },
        {
            "x": -4.944421460990082,
            "density": 0.02277279946360426
        },
        {
            "x": -4.594738339236905,
            "density": 0.02252333914473462
        },
        {
            "x": -4.245055217483724,
            "density": 0.0222153068006731
        },
        {
            "x": -3.8953720957305435,
            "density": 0.021861503083170062
        },
        {
            "x": -3.5456889739773665,
            "density": 0.021472150391089358
        },
        {
            "x": -3.196005852224186,
            "density": 0.021054256166368628
        },
        {
            "x": -2.8463227304710053,
            "density": 0.020611999434468637
        },
        {
            "x": -2.496639608717828,
            "density": 0.020147929981715614
        },
        {
            "x": -2.1469564869646476,
            "density": 0.019664588871982965
        },
        {
            "x": -1.797273365211467,
            "density": 0.019166091661386973
        },
        {
            "x": -1.44759024345829,
            "density": 0.018659264127203562
        },
        {
            "x": -1.0979071217051093,
            "density": 0.018154057879403322
        },
        {
            "x": -0.7482239999519287,
            "density": 0.017663156162623688
        },
        {
            "x": -0.3985408781987516,
            "density": 0.017200862018086214
        },
        {
            "x": -0.048857756445571,
            "density": 0.016781504161655757
        },
        {
            "x": 0.3008253653076096,
            "density": 0.016417678061020437
        },
        {
            "x": 0.6505084870607867,
            "density": 0.016118654448664713
        },
        {
            "x": 1.0001916088139673,
            "density": 0.015889241640384636
        },
        {
            "x": 1.349874730567148,
            "density": 0.01572929676192522
        },
        {
            "x": 1.699557852320325,
            "density": 0.01563396366673128
        },
        {
            "x": 2.0492409740735056,
            "density": 0.015594592224630043
        },
        {
            "x": 2.398924095826686,
            "density": 0.015600183841580085
        },
        {
            "x": 2.7486072175798633,
            "density": 0.015639127808339048
        },
        {
            "x": 3.098290339333044,
            "density": 0.015700954240065956
        },
        {
            "x": 3.4479734610862245,
            "density": 0.015777837615140643
        },
        {
            "x": 3.7976565828394016,
            "density": 0.01586563803960026
        },
        {
            "x": 4.147339704592582,
            "density": 0.01596435457452268
        },
        {
            "x": 4.497022826345759,
            "density": 0.016077968071473082
        },
        {
            "x": 4.84670594809894,
            "density": 0.016213747867777017
        },
        {
            "x": 5.1963890698521205,
            "density": 0.01638116689501185
        },
        {
            "x": 5.5460721916052975,
            "density": 0.016590600355948323
        },
        {
            "x": 5.895755313358478,
            "density": 0.016851973181206483
        },
        {
            "x": 6.245438435111659,
            "density": 0.017173482604200267
        },
        {
            "x": 6.595121556864836,
            "density": 0.017560474601300585
        },
        {
            "x": 6.944804678618016,
            "density": 0.01801451787806287
        },
        {
            "x": 7.294487800371197,
            "density": 0.01853271037222081
        },
        {
            "x": 7.644170922124374,
            "density": 0.019107271341702876
        },
        {
            "x": 7.993854043877555,
            "density": 0.01972550320901705
        },
        {
            "x": 8.343537165630735,
            "density": 0.02037022825714603
        },
        {
            "x": 8.693220287383912,
            "density": 0.021020792437346513
        },
        {
            "x": 9.042903409137093,
            "density": 0.02165466781938489
        },
        {
            "x": 9.392586530890274,
            "density": 0.022249578964622044
        },
        {
            "x": 9.742269652643454,
            "density": 0.022785947291760977
        },
        {
            "x": 10.091952774396635,
            "density": 0.02324932557857599
        },
        {
            "x": 10.441635896149808,
            "density": 0.023632420580786604
        },
        {
            "x": 10.791319017902989,
            "density": 0.02393630642137605
        },
        {
            "x": 11.14100213965617,
            "density": 0.024170528167021966
        },
        {
            "x": 11.49068526140935,
            "density": 0.024351973317788583
        },
        {
            "x": 11.84036838316253,
            "density": 0.02450261491810801
        },
        {
            "x": 12.190051504915704,
            "density": 0.024646453707128153
        },
        {
            "x": 12.539734626668885,
            "density": 0.024806154594196723
        },
        {
            "x": 12.889417748422066,
            "density": 0.024999941984401065
        },
        {
            "x": 13.239100870175246,
            "density": 0.025239269414285708
        },
        {
            "x": 13.588783991928427,
            "density": 0.025527621499635725
        },
        {
            "x": 13.938467113681607,
            "density": 0.025860578136628315
        },
        {
            "x": 14.288150235434781,
            "density": 0.026227027988680048
        },
        {
            "x": 14.637833357187962,
            "density": 0.02661121865694878
        },
        {
            "x": 14.987516478941142,
            "density": 0.026995218386035153
        },
        {
            "x": 15.337199600694323,
            "density": 0.027361355793002303
        },
        {
            "x": 15.686882722447503,
            "density": 0.027694286488494996
        },
        {
            "x": 16.036565844200684,
            "density": 0.027982470960990782
        },
        {
            "x": 16.386248965953857,
            "density": 0.028218989340472844
        },
        {
            "x": 16.735932087707038,
            "density": 0.02840172574064842
        },
        {
            "x": 17.08561520946022,
            "density": 0.028533008823121438
        },
        {
            "x": 17.4352983312134,
            "density": 0.028618802446420642
        },
        {
            "x": 17.78498145296658,
            "density": 0.028667526418729005
        },
        {
            "x": 18.13466457471976,
            "density": 0.028688583428680504
        },
        {
            "x": 18.484347696472934,
            "density": 0.028690694783376793
        },
        {
            "x": 18.834030818226115,
            "density": 0.028680204270453185
        },
        {
            "x": 19.183713939979295,
            "density": 0.02865957400504439
        },
        {
            "x": 19.533397061732476,
            "density": 0.028626333536946554
        },
        {
            "x": 19.883080183485657,
            "density": 0.02857272164055207
        },
        {
            "x": 20.232763305238837,
            "density": 0.0284861652396121
        },
        {
            "x": 20.58244642699201,
            "density": 0.028350585052596244
        },
        {
            "x": 20.93212954874519,
            "density": 0.028148341234985382
        },
        {
            "x": 21.281812670498372,
            "density": 0.027862485959129817
        },
        {
            "x": 21.631495792251553,
            "density": 0.027478919615102418
        },
        {
            "x": 21.981178914004733,
            "density": 0.02698807666483932
        },
        {
            "x": 22.330862035757907,
            "density": 0.02638588775379993
        },
        {
            "x": 22.680545157511087,
            "density": 0.025673938771454942
        },
        {
            "x": 23.030228279264268,
            "density": 0.024858921868433918
        },
        {
            "x": 23.37991140101745,
            "density": 0.023951598615144842
        },
        {
            "x": 23.72959452277063,
            "density": 0.022965543382171865
        },
        {
            "x": 24.07927764452381,
            "density": 0.02191590680926906
        },
        {
            "x": 24.428960766276983,
            "density": 0.020818361286212863
        },
        {
            "x": 24.778643888030164,
            "density": 0.019688300455717785
        },
        {
            "x": 25.128327009783344,
            "density": 0.01854029519906881
        },
        {
            "x": 25.478010131536525,
            "density": 0.017387774198777767
        },
        {
            "x": 25.827693253289706,
            "density": 0.01624289288132449
        },
        {
            "x": 26.177376375042886,
            "density": 0.015116562479315355
        },
        {
            "x": 26.52705949679606,
            "density": 0.014018612615854638
        },
        {
            "x": 26.87674261854924,
            "density": 0.012958047434229923
        },
        {
            "x": 27.22642574030242,
            "density": 0.011943331530453462
        },
        {
            "x": 27.5761088620556,
            "density": 0.010982621898295727
        },
        {
            "x": 27.925791983808782,
            "density": 0.010083860685186147
        },
        {
            "x": 28.275475105561963,
            "density": 0.00925466821732995
        },
        {
            "x": 28.625158227315136,
            "density": 0.008502022576848605
        },
        {
            "x": 28.974841349068317,
            "density": 0.007831767638439551
        },
        {
            "x": 29.324524470821498,
            "density": 0.007248039008807436
        },
        {
            "x": 29.674207592574678,
            "density": 0.0067527230293818
        },
        {
            "x": 30.02389071432786,
            "density": 0.006345061779333325
        },
        {
            "x": 30.37357383608104,
            "density": 0.00602148920857457
        },
        {
            "x": 30.723256957834213,
            "density": 0.005775738794804369
        },
        {
            "x": 31.072940079587394,
            "density": 0.005599212821179171
        },
        {
            "x": 31.422623201340574,
            "density": 0.005481558293223585
        },
        {
            "x": 31.772306323093755,
            "density": 0.005411362815821385
        },
        {
            "x": 32.12198944484693,
            "density": 0.005376870243479459
        },
        {
            "x": 32.471672566600105,
            "density": 0.005366622071743392
        },
        {
            "x": 32.82135568835329,
            "density": 0.005369954618649463
        },
        {
            "x": 33.17103881010647,
            "density": 0.005377319109971774
        },
        {
            "x": 33.520721931859654,
            "density": 0.005380433838710434
        },
        {
            "x": 33.87040505361283,
            "density": 0.005372314481914818
        },
        {
            "x": 34.220088175366016,
            "density": 0.005347250244251514
        },
        {
            "x": 34.56977129711919,
            "density": 0.005300792639953265
        },
        {
            "x": 34.91945441887236,
            "density": 0.005229799510500798
        },
        {
            "x": 35.26913754062555,
            "density": 0.005132536266455975
        },
        {
            "x": 35.618820662378724,
            "density": 0.005008793066991644
        },
        {
            "x": 35.96850378413191,
            "density": 0.004859947033146641
        },
        {
            "x": 36.318186905885085,
            "density": 0.004688895490518456
        },
        {
            "x": 36.66787002763826,
            "density": 0.004499813482679135
        },
        {
            "x": 37.017553149391446,
            "density": 0.004297738691549095
        },
        {
            "x": 37.36723627114462,
            "density": 0.004088042316997635
        },
        {
            "x": 37.71691939289781,
            "density": 0.0038758850693550047
        },
        {
            "x": 38.06660251465098,
            "density": 0.003665767614769924
        },
        {
            "x": 38.41628563640417,
            "density": 0.0034612600209493146
        },
        {
            "x": 38.76596875815734,
            "density": 0.0032649433589776386
        },
        {
            "x": 39.115651879910516,
            "density": 0.003078536617309945
        },
        {
            "x": 39.4653350016637,
            "density": 0.002903133991835205
        },
        {
            "x": 39.81501812341688,
            "density": 0.0027394566986688237
        },
        {
            "x": 40.164701245170065,
            "density": 0.00258803449801028
        },
        {
            "x": 40.51438436692324,
            "density": 0.002449268622370363
        },
        {
            "x": 40.86406748867641,
            "density": 0.0023233754945798236
        },
        {
            "x": 41.2137506104296,
            "density": 0.0022102533238768742
        },
        {
            "x": 41.56343373218277,
            "density": 0.0021093389495917105
        },
        {
            "x": 41.913116853935946,
            "density": 0.0020195248046099646
        },
        {
            "x": 42.262799975689134,
            "density": 0.0019391875980892858
        },
        {
            "x": 42.61248309744231,
            "density": 0.0018663485146807911
        },
        {
            "x": 42.962166219195495,
            "density": 0.001798948780708225
        },
        {
            "x": 43.31184934094867,
            "density": 0.001735193146290963
        },
        {
            "x": 43.66153246270186,
            "density": 0.0016738937149081237
        },
        {
            "x": 44.01121558445503,
            "density": 0.0016147412910117263
        },
        {
            "x": 44.360898706208204,
            "density": 0.0015584417886124616
        },
        {
            "x": 44.71058182796139,
            "density": 0.0015066792657148435
        },
        {
            "x": 45.060264949714565,
            "density": 0.0014619002861115569
        },
        {
            "x": 45.40994807146775,
            "density": 0.0014269499677510857
        },
        {
            "x": 45.759631193220926,
            "density": 0.0014046206382793268
        },
        {
            "x": 46.1093143149741,
            "density": 0.0013971924398908364
        },
        {
            "x": 46.45899743672729,
            "density": 0.0014060468600696505
        },
        {
            "x": 46.80868055848046,
            "density": 0.0014314182203125187
        },
        {
            "x": 47.15836368023365,
            "density": 0.001472318214585914
        },
        {
            "x": 47.50804680198682,
            "density": 0.0015266318935314098
        },
        {
            "x": 47.857729923739996,
            "density": 0.0015913491052027228
        },
        {
            "x": 48.20741304549318,
            "density": 0.0016628717816631277
        },
        {
            "x": 48.55709616724636,
            "density": 0.0017373301161998484
        },
        {
            "x": 48.906779288999545,
            "density": 0.0018108506523746256
        },
        {
            "x": 49.25646241075272,
            "density": 0.0018797428990121852
        },
        {
            "x": 49.606145532505906,
            "density": 0.001940600900382236
        },
        {
            "x": 49.95582865425908,
            "density": 0.0019903432586709925
        },
        {
            "x": 50.30551177601225,
            "density": 0.002026231473238244
        },
        {
            "x": 50.65519489776544,
            "density": 0.0020459075379203277
        },
        {
            "x": 51.004878019518614,
            "density": 0.0020474777081907905
        },
        {
            "x": 51.3545611412718,
            "density": 0.0020296451801497858
        },
        {
            "x": 51.704244263024975,
            "density": 0.001991868370140071
        },
        {
            "x": 52.05392738477815,
            "density": 0.0019345024803093217
        },
        {
            "x": 52.40361050653134,
            "density": 0.0018588767410295576
        },
        {
            "x": 52.75329362828451,
            "density": 0.0017672702358544853
        },
        {
            "x": 53.1029767500377,
            "density": 0.0016627723165134202
        },
        {
            "x": 53.45265987179087,
            "density": 0.0015490418744964782
        },
        {
            "x": 53.80234299354406,
            "density": 0.0014300041502777836
        },
        {
            "x": 54.15202611529723,
            "density": 0.001309536931957142
        },
        {
            "x": 54.501709237050406,
            "density": 0.001191196615327838
        },
        {
            "x": 54.851392358803594,
            "density": 0.0010780203179916092
        },
        {
            "x": 55.20107548055677,
            "density": 0.0009724186659186467
        },
        {
            "x": 55.550758602309955,
            "density": 0.0008761522252758336
        },
        {
            "x": 55.90044172406313,
            "density": 0.0007903690465884263
        },
        {
            "x": 56.2501248458163,
            "density": 0.0007156747289382669
        },
        {
            "x": 56.59980796756949,
            "density": 0.0006522096313326185
        },
        {
            "x": 56.94949108932266,
            "density": 0.0005997174214724487
        },
        {
            "x": 57.29917421107585,
            "density": 0.0005576008072774647
        },
        {
            "x": 57.648857332829024,
            "density": 0.0005249699954355902
        },
        {
            "x": 57.9985404545822,
            "density": 0.0005006944128850131
        },
        {
            "x": 58.348223576335386,
            "density": 0.00048346755208365945
        },
        {
            "x": 58.69790669808856,
            "density": 0.0004718892667809072
        },
        {
            "x": 59.04758981984175,
            "density": 0.00046456164525926757
        },
        {
            "x": 59.39727294159492,
            "density": 0.00046018667947622053
        },
        {
            "x": 59.74695606334811,
            "density": 0.00045764925033296255
        },
        {
            "x": 60.09663918510128,
            "density": 0.000456069463657715
        },
        {
            "x": 60.446322306854455,
            "density": 0.0004548144421355454
        },
        {
            "x": 60.79600542860764,
            "density": 0.000453469687832152
        },
        {
            "x": 61.145688550360816,
            "density": 0.0004517808741798629
        },
        {
            "x": 61.495371672114004,
            "density": 0.00044958466411774696
        },
        {
            "x": 61.84505479386718,
            "density": 0.00044674900103235945
        },
        {
            "x": 62.19473791562035,
            "density": 0.0004431384488258388
        },
        {
            "x": 62.54442103737354,
            "density": 0.0004386102263884766
        },
        {
            "x": 62.89410415912671,
            "density": 0.00043303518717298736
        },
        {
            "x": 63.2437872808799,
            "density": 0.0004263293048082489
        },
        {
            "x": 63.59347040263307,
            "density": 0.0004184783580760004
        },
        {
            "x": 63.94315352438626,
            "density": 0.00040954233023277476
        },
        {
            "x": 64.29283664613943,
            "density": 0.0003996348809630721
        },
        {
            "x": 64.64251976789261,
            "density": 0.00038888363139699027
        },
        {
            "x": 64.9922028896458,
            "density": 0.0003773850155751315
        },
        {
            "x": 65.34188601139897,
            "density": 0.00036517023519385723
        },
        {
            "x": 65.69156913315216,
            "density": 0.00035219557730996906
        },
        {
            "x": 66.04125225490533,
            "density": 0.00033836237619968364
        },
        {
            "x": 66.3909353766585,
            "density": 0.00032356213083665174
        },
        {
            "x": 66.74061849841169,
            "density": 0.00030773406444416164
        },
        {
            "x": 67.09030162016487,
            "density": 0.000290918334969774
        },
        {
            "x": 67.43998474191805,
            "density": 0.00027328925336695574
        },
        {
            "x": 67.78966786367123,
            "density": 0.00025515859050166635
        },
        {
            "x": 68.1393509854244,
            "density": 0.00023694735175723133
        },
        {
            "x": 68.48903410717759,
            "density": 0.00021913267794877302
        },
        {
            "x": 68.83871722893076,
            "density": 0.00020218246163327132
        },
        {
            "x": 69.18840035068395,
            "density": 0.00018649244967972956
        },
        {
            "x": 69.53808347243712,
            "density": 0.00017233886458533303
        },
        {
            "x": 69.88776659419031,
            "density": 0.00015985485782773326
        },
        {
            "x": 70.23744971594348,
            "density": 0.00014903301969191804
        },
        {
            "x": 70.58713283769666,
            "density": 0.00013975041969821697
        },
        {
            "x": 70.93681595944985,
            "density": 0.000131808541564662
        },
        {
            "x": 71.28649908120302,
            "density": 0.00012497862320877116
        },
        {
            "x": 71.6361822029562,
            "density": 0.00011904324568074446
        },
        {
            "x": 71.98586532470938,
            "density": 0.00011382699429286773
        },
        {
            "x": 72.33554844646255,
            "density": 0.00010921192926870045
        },
        {
            "x": 72.68523156821574,
            "density": 0.0001051368143618854
        },
        {
            "x": 73.03491468996891,
            "density": 0.00010158209833770686
        },
        {
            "x": 73.3845978117221,
            "density": 9.85452024849531e-05
        },
        {
            "x": 73.73428093347528,
            "density": 9.601245229802305e-05
        },
        {
            "x": 74.08396405522846,
            "density": 9.393469695386962e-05
        },
        {
            "x": 74.43364717698164,
            "density": 9.221300736818796e-05
        },
        {
            "x": 74.78333029873481,
            "density": 9.069872917706414e-05
        },
        {
            "x": 75.133013420488,
            "density": 8.920883027289287e-05
        },
        {
            "x": 75.48269654224117,
            "density": 8.75535805506304e-05
        },
        {
            "x": 75.83237966399436,
            "density": 8.557011328565605e-05
        },
        {
            "x": 76.18206278574753,
            "density": 8.3153377478232e-05
        },
        {
            "x": 76.5317459075007,
            "density": 8.027613781106593e-05
        },
        {
            "x": 76.8814290292539,
            "density": 7.699216074067637e-05
        },
        {
            "x": 77.23111215100707,
            "density": 7.342098079080405e-05
        },
        {
            "x": 77.58079527276026,
            "density": 6.971752677949578e-05
        },
        {
            "x": 77.93047839451343,
            "density": 6.603401159227788e-05
        },
        {
            "x": 78.2801615162666,
            "density": 6.248364276953151e-05
        },
        {
            "x": 78.62984463801979,
            "density": 5.91152522237302e-05
        },
        {
            "x": 78.97952775977296,
            "density": 5.5905000603859154e-05
        },
        {
            "x": 79.32921088152615,
            "density": 5.276674565362659e-05
        },
        {
            "x": 79.67889400327932,
            "density": 4.9577796847863264e-05
        },
        {
            "x": 80.02857712503251,
            "density": 4.621298412544661e-05
        },
        {
            "x": 80.37826024678569,
            "density": 4.2578253087834643e-05
        },
        {
            "x": 80.72794336853886,
            "density": 3.86357123401717e-05
        },
        {
            "x": 81.07762649029205,
            "density": 3.441482380215088e-05
        }
    ]
}